flask_resty/__init__.py
flask_resty/api.py
flask_resty/authentication.py
flask_resty/authorization.py
flask_resty/context.py
flask_resty/decorators.py
flask_resty/exceptions.py
flask_resty/fields.py
flask_resty/filtering.py
flask_resty/jwt.py
flask_resty/meta.py
flask_resty/pagination.py
flask_resty/related.py
flask_resty/shell.py
flask_resty/sorting.py
flask_resty/testing.py
flask_resty/utils.py
flask_resty/view.py
flask_resty-6.0.0.dist-info/licenses/LICENSE
flask_resty-6.0.0.dist-info/METADATA
flask_resty-6.0.0.dist-info/WHEEL
flask_resty-6.0.0.dist-info/entry_points.txt
flask_resty-6.0.0.dist-info/top_level.txt
flask_resty-6.0.0.dist-info/RECORD
